kedro_argo/__init__.py
kedro_argo/__main__.py
kedro_argo/cli.py
kedro_argo/templates/argo_template.yaml
kedro_argo-0.0.9.dist-info/AUTHORS.rst
kedro_argo-0.0.9.dist-info/LICENSE
kedro_argo-0.0.9.dist-info/METADATA
kedro_argo-0.0.9.dist-info/WHEEL
kedro_argo-0.0.9.dist-info/entry_points.txt
kedro_argo-0.0.9.dist-info/top_level.txt
kedro_argo-0.0.9.dist-info/RECORD
