Metadata-Version: 2.1
Name: kedro-argo
Version: 0.0.9
Summary: Converting kedro pipelines to argo pipelines.
Home-page: https://github.com/nraw/kedro-argo
Author: Andrej Marsic
Author-email: marsic.andrej@gmail.com
License: BSD-3-Clause
Project-URL: Documentation, https://kedro-argo.readthedocs.io/
Project-URL: Changelog, https://kedro-argo.readthedocs.io/en/latest/changelog.html
Project-URL: Issue Tracker, https://github.com/nraw/kedro-argo/issues
Platform: UNKNOWN
Classifier: Development Status :: 5 - Production/Stable
Classifier: Intended Audience :: Developers
Classifier: License :: OSI Approved :: BSD License
Classifier: Operating System :: Unix
Classifier: Operating System :: POSIX
Classifier: Operating System :: Microsoft :: Windows
Classifier: Programming Language :: Python
Classifier: Programming Language :: Python :: 3
Classifier: Programming Language :: Python :: 3.6
Classifier: Programming Language :: Python :: 3.7
Classifier: Programming Language :: Python :: Implementation :: CPython
Classifier: Topic :: Utilities
Requires-Python: >=3.6, <3.8
Requires-Dist: click (>=7.0.0)
Requires-Dist: kedro (>=0.15.5)
